{
  "match_id": "2026-05-15_alaves-vs-oviedo",
  "home": "Alavés",
  "away": "Real Oviedo",
  "league": "ESP1",
  "date": "2026-05-15",
  "home_stats": {
    "team": "Alaves",
    "mp": 38,
    "w": 11,
    "d": 10,
    "l": 17,
    "gf": 44,
    "ga": 56,
    "gd": -12,
    "pts": 43,
    "avg": {
      "gf": 1.16,
      "ga": 1.47,
      "corners_for": 5.05,
      "corners_against": 5.0,
      "total_corners": 10.05,
      "shots": 12.16,
      "shots_against": 12.47,
      "shots_target": 4.03,
      "shots_target_against": 4.05,
      "fouls": 14.92,
      "fouls_against": 13.53,
      "yellows": 2.5,
      "opponent_yellows": 2.16,
      "total_match_cards": 4.66
    },
    "avg_home": {
      "gf": 1.32,
      "ga": 1.32,
      "corners_for": 6.16,
      "corners_against": 4.26,
      "over_25_pct": 57.9
    },
    "avg_away": {
      "gf": 1.0,
      "ga": 1.63,
      "corners_for": 3.95,
      "corners_against": 5.74,
      "over_25_pct": 42.1
    },
    "pct": {
      "over_15": 71.1,
      "over_25": 50.0,
      "over_35": 23.7,
      "btts": 63.2,
      "clean_sheet": 13.2,
      "failed_to_score": 26.3
    },
    "avg_ht": {
      "gf_1h": 0.53,
      "ga_1h": 0.5,
      "gf_2h": 0.63,
      "ga_2h": 0.97,
      "total_1h": 1.03,
      "total_2h": 1.61
    },
    "pct_ht": {
      "over_05_1h": 65.8,
      "over_15_1h": 23.7,
      "over_05_2h": 78.9,
      "over_15_2h": 52.6,
      "btts_1h": 21.1,
      "btts_2h": 36.8
    },
    "xg": 44.0,
    "xga": 46.5,
    "xg_diff": -4.0,
    "xga_diff": 6.5,
    "yellow_cards_total": 75,
    "red_cards_total": null,
    "yc_per_match": 2.21
  },
  "away_stats": {
    "team": "Oviedo",
    "mp": 38,
    "w": 6,
    "d": 11,
    "l": 21,
    "gf": 26,
    "ga": 60,
    "gd": -34,
    "pts": 29,
    "avg": {
      "gf": 0.68,
      "ga": 1.58,
      "corners_for": 3.95,
      "corners_against": 5.55,
      "total_corners": 9.5,
      "shots": 10.0,
      "shots_against": 14.87,
      "shots_target": 3.13,
      "shots_target_against": 5.53,
      "fouls": 12.47,
      "fouls_against": 11.66,
      "yellows": 2.13,
      "opponent_yellows": 1.42,
      "total_match_cards": 3.55
    },
    "avg_home": {
      "gf": 0.47,
      "ga": 0.95,
      "corners_for": 4.63,
      "corners_against": 4.84,
      "over_25_pct": 21.1
    },
    "avg_away": {
      "gf": 0.89,
      "ga": 2.21,
      "corners_for": 3.26,
      "corners_against": 6.26,
      "over_25_pct": 57.9
    },
    "pct": {
      "over_15": 65.8,
      "over_25": 39.5,
      "over_35": 15.8,
      "btts": 31.6,
      "clean_sheet": 26.3,
      "failed_to_score": 55.3
    },
    "avg_ht": {
      "gf_1h": 0.32,
      "ga_1h": 0.68,
      "gf_2h": 0.37,
      "ga_2h": 0.89,
      "total_1h": 1.0,
      "total_2h": 1.26
    },
    "pct_ht": {
      "over_05_1h": 68.4,
      "over_15_1h": 26.3,
      "over_05_2h": 60.5,
      "over_15_2h": 39.5,
      "btts_1h": 7.9,
      "btts_2h": 13.2
    },
    "xg": 36.2,
    "xga": 56.8,
    "xg_diff": -10.2,
    "xga_diff": -2.8,
    "yellow_cards_total": 67,
    "red_cards_total": null,
    "yc_per_match": 1.97
  },
  "generated": "2026-07-16T20:03:21Z"
}